{"updated": "2026-04-12 15:35 UTC", "portfolio": {"curve": [100000.0, 99950.99, 99322.67, 99866.81, 99613.85, 100979.34, 101464.54, 101253.84, 101279.57, 100967.58, 99743.96, 100060.36, 101040.05, 99822.49, 100696.05, 98494.57, 98906.32, 99916.02, 99514.07, 98801.52, 97832.17, 97973.47, 99667.92, 100454.97, 100332.32, 100276.82, 101369.67, 100399.96, 101462.16, 104204.21, 104863.46, 106362.71, 107448.36, 107784.21, 106978.36, 104252.96, 102733.71, 102214.21, 102147.71, 104079.41, 102421.41, 101865.51, 101671.71, 99874.26, 98913.21, 100698.51, 99739.41, 100395.77, 100751.79, 100614.02, 101241.91, 97347.49, 102081.89, 103069.03, 102369.65, 102124.34, 103633.86, 104228.32, 102918.2, 102061.91, 101270.8, 101299.75, 100923.9, 101465.34, 100056.71, 100140.94, 101595.79, 102189.18, 101860.85, 101928.34, 100350.49, 99124.79, 96785.43, 98609.63, 98669.63, 97897.43, 98347.63, 99036.83, 100807.83, 97752.73, 96604.73, 98499.23, 98401.83, 97211.73, 98562.28, 96119.79, 97518.69, 98173.48, 97802.09, 97543.59, 99309.25, 99601.32, 99809.65, 101463.74, 100449.09, 101674.09, 102541.33], "win_rate": 40.0, "total_trades": 10, "profit": 2541.33, "ledger": [{"date": "2025-12-10", "symbol": "SONACOMS.NS", "pnl": -2046.3, "result": "LOSS"}, {"date": "2025-12-29", "symbol": "MCX.NS", "pnl": 2714.9, "result": "WIN"}, {"date": "2026-01-21", "symbol": "SAILIFE.NS", "pnl": -2066.76, "result": "LOSS"}, {"date": "2026-01-28", "symbol": "JINDALSTEL.NS", "pnl": 2933.53, "result": "WIN"}, {"date": "2026-02-02", "symbol": "ABCAPITAL.NS", "pnl": -2025.72, "result": "LOSS"}, {"date": "2026-02-02", "symbol": "BSE.NS", "pnl": -1836.5, "result": "LOSS"}, {"date": "2026-02-03", "symbol": "NAM-INDIA.NS", "pnl": 2974.3, "result": "WIN"}, {"date": "2026-03-02", "symbol": "ANGELONE.NS", "pnl": -2138.14, "result": "LOSS"}, {"date": "2026-03-04", "symbol": "CUB.NS", "pnl": -2029.55, "result": "LOSS"}, {"date": "2026-03-20", "symbol": "CCL.NS", "pnl": 2825.73, "result": "WIN"}]}, "tickers": {"3MINDIA": 100.0, "ABB": 0, "AIAENG": 0, "APLAPOLLO": 67.0, "AUBANK": 50.0, "ADANIPOWER": 0.0, "ABCAPITAL": 33.0, "ABSLAMC": 0.0, "ALKEM": 0, "ANANDRATHI": 0, "ANGELONE": 0.0, "ANURAS": 67.0, "APARINDS": 0.0, "ASHOKLEY": 100.0, "ASTRAL": 33.0, "ATHERENERG": 0, "AIIL": 0.0, "AXISBANK": 33.0, "BSE": 33.0, "BAJAJ-AUTO": 100.0, "BANKINDIA": 75.0, "MAHABANK": 50.0, "BELRISE": 0, "BHARATFORG": 0, "BHEL": 0.0, "CCL": 67.0, "CANBK": 0.0, "CHENNPETRO": 100.0, "CUB": 25.0, "COALINDIA": 100.0, "CRAFTSMAN": 100.0, "CUMMINSIND": 100.0, "DATAPATTNS": 33.0, "EMCURE": 0, "ENGINERSIN": 0.0, "ETERNAL": 0.0, "FEDERALBNK": 0, "FORCEMOT": 60.0, "GVT&D": 100.0, "GLENMARK": 0.0, "GPIL": 67.0, "GRANULES": 0.0, "GRAPHITE": 67.0, "GESHIP": 67.0, "HBLENGINE": 50.0, "HFCL": 0, "HINDALCO": 50.0, "HINDCOPPER": 50.0, "HINDZINC": 0.0, "POWERINDIA": 33.0, "INDIANB": 100.0, "INDUSTOWER": 0, "INDUSINDBK": 0.0, "JBCHEPHARM": 33.0, "JKTYRE": 67.0, "J&KBANK": 50.0, "JINDALSTEL": 33.0, "KARURVYSYA": 100.0, "KIRLOSENG": 100.0, "LAURUSLABS": 67.0, "LLOYDSME": 0, "LUPIN": 0.0, "MRPL": 50.0, "MCX": 50.0, "MUTHOOTFIN": 50.0, "NATCOPHARM": 0.0, "NMDC": 0.0, "NTPC": 0.0, "NATIONALUM": 67.0, "NAVINFLUOR": 50.0, "NAM-INDIA": 50.0, "ONGC": 0, "OIL": 50.0, "PTCIL": 25.0, "PHOENIXLTD": 100.0, "PFC": 0.0, "POWERGRID": 0.0, "RRKABEL": 100.0, "RBLBANK": 100.0, "SBILIFE": 50.0, "SAILIFE": 50.0, "MOTHERSON": 100.0, "SCHNEIDER": 0.0, "SCI": 50.0, "SHRIRAMFIN": 33.0, "SONACOMS": 50.0, "SBIN": 100.0, "SAIL": 0, "SUNDARMFIN": 33.0, "TVSMOTOR": 50.0, "TATASTEEL": 50.0, "TITAN": 50.0, "TORNTPHARM": 100.0, "TORNTPOWER": 100.0, "UNIONBANK": 100.0, "VTL": 0.0, "VEDL": 50.0, "IDEA": 50.0, "WELCORP": 50.0, "ZYDUSWELL": 40.0}}