{"updated": "2026-02-26 15:53 UTC", "portfolio": {"curve": [100000.0, 99922.09, 100066.82, 100178.18, 100251.39, 100322.88, 101197.81, 100356.03, 98621.97, 101347.96, 101214.98, 100090.16, 100317.76, 101484.97, 101492.08, 105083.15, 106306.37, 105758.7, 105079.57, 105439.34, 103592.41, 103348.09, 101754.05, 103405.78, 104454.84, 104720.0, 105566.13, 105699.65, 106293.92, 107521.43, 106546.5, 104830.43, 103251.22, 105265.52, 106835.85, 106306.84, 105387.98, 104621.13, 104129.65, 103112.22, 105027.59, 104583.72, 102914.92, 103761.69, 103132.16, 103761.48, 105224.23, 104098.39, 105131.28, 104191.24, 104697.96, 104914.18, 105471.19, 105652.86, 105010.69, 105045.51, 106082.14, 106051.24, 105530.6, 106502.46, 107928.42, 107572.43, 107728.83, 107394.21, 106296.27, 104824.14, 105872.68, 105642.31, 106035.3, 107903.06, 107385.5, 106470.52, 105366.16, 105158.1, 105864.06, 105396.96, 105890.76, 106508.28, 106941.68, 107686.0, 106517.44, 108466.64, 108683.08, 108526.42, 108429.7, 109652.46, 110039.71, 109943.33, 109627.13, 108889.33, 109513.61, 109667.91, 109902.99, 109281.69, 109198.79, 109069.01, 109157.58, 109160.11, 109459.93], "win_rate": 62.5, "total_trades": 8, "profit": 9459.93, "ledger": [{"date": "2025-10-20", "symbol": "RBLBANK.NS", "pnl": 2925.39, "result": "WIN"}, {"date": "2025-11-06", "symbol": "KEI.NS", "pnl": -2022.19, "result": "LOSS"}, {"date": "2025-11-12", "symbol": "MRPL.NS", "pnl": 2902.77, "result": "WIN"}, {"date": "2025-12-08", "symbol": "POLYCAB.NS", "pnl": -1835.78, "result": "LOSS"}, {"date": "2025-12-16", "symbol": "KIRLOSENG.NS", "pnl": 2993.58, "result": "WIN"}, {"date": "2025-12-22", "symbol": "CHOLAFIN.NS", "pnl": -2099.67, "result": "LOSS"}, {"date": "2025-12-31", "symbol": "HEG.NS", "pnl": 2924.24, "result": "WIN"}, {"date": "2026-02-10", "symbol": "BSE.NS", "pnl": 2951.92, "result": "WIN"}]}, "tickers": {"3MINDIA": 100.0, "ABB": 0, "AIAENG": 0, "APLAPOLLO": 40.0, "AUBANK": 100.0, "AARTIIND": 0, "ADANIPOWER": 0.0, "ABCAPITAL": 50.0, "ALKEM": 0, "ANANDRATHI": 0, "APARINDS": 50.0, "ASHOKLEY": 67.0, "ASTRAL": 33.0, "ATHERENERG": 0, "AIIL": 0.0, "AXISBANK": 50.0, "BSE": 29.0, "BANKBARODA": 100.0, "BANKINDIA": 75.0, "MAHABANK": 100.0, "BEL": 50.0, "BHARATFORG": 0, "BHEL": 0.0, "BPCL": 50.0, "CCL": 67.0, "CANFINHOME": 0.0, "CANBK": 0.0, "CEATLTD": 50.0, "CHENNPETRO": 100.0, "CHOLAFIN": 0.0, "CUB": 33.0, "COALINDIA": 0, "CRAFTSMAN": 100.0, "CUMMINSIND": 100.0, "DATAPATTNS": 33.0, "EICHERMOT": 50.0, "EMCURE": 0, "FEDERALBNK": 0.0, "FORCEMOT": 60.0, "GVT&D": 100.0, "GRANULES": 0.0, "GRAPHITE": 67.0, "GESHIP": 67.0, "GMDCLTD": 50.0, "HEG": 67.0, "HBLENGINE": 50.0, "HINDALCO": 67.0, "HINDCOPPER": 50.0, "HINDZINC": 0.0, "POWERINDIA": 33.0, "IDBI": 100.0, "INDIANB": 100.0, "IOC": 100.0, "INDUSTOWER": 0, "INDUSINDBK": 0, "JBCHEPHARM": 0.0, "JKTYRE": 50.0, "JSWSTEEL": 67.0, "J&KBANK": 0.0, "JINDALSTEL": 50.0, "KEI": 0.0, "KARURVYSYA": 100.0, "KIRLOSENG": 100.0, "LTF": 0.0, "LT": 0.0, "LAURUSLABS": 40.0, "LUPIN": 0.0, "M&MFIN": 67.0, "MRPL": 50.0, "MCX": 50.0, "MUTHOOTFIN": 50.0, "NMDC": 0.0, "NATIONALUM": 67.0, "NAVINFLUOR": 67.0, "NETWEB": 50.0, "ONGC": 0, "OIL": 50.0, "PTCIL": 25.0, "PETRONET": 0.0, "PHOENIXLTD": 100.0, "POLYCAB": 0, "PNB": 100.0, "RBLBANK": 100.0, "SAMMAANCAP": 25.0, "MOTHERSON": 0, "SCI": 50.0, "SHRIRAMFIN": 33.0, "SONACOMS": 50.0, "SBIN": 100.0, "SAIL": 0, "TVSMOTOR": 33.0, "TATASTEEL": 67.0, "TITAN": 50.0, "TORNTPHARM": 100.0, "TORNTPOWER": 0, "TRIVENI": 0, "UNIONBANK": 100.0, "VTL": 0.0, "VEDL": 50.0, "IDEA": 50.0}}